ai_toolkit/__init__.py
ai_toolkit/args.py
ai_toolkit/metric_tracker.py
ai_toolkit/py.typed
ai_toolkit/test.py
ai_toolkit/train.py
ai_toolkit/util.py
ai_toolkit/verify.py
ai_toolkit/viz.py
ai_toolkit/datasets/__init__.py
ai_toolkit/datasets/dataset.py
ai_toolkit/datasets/dataset_cnn.py
ai_toolkit/datasets/dataset_lstm.py
ai_toolkit/datasets/dataset_penn.py
ai_toolkit/datasets/dataset_rnn.py
ai_toolkit/losses/__init__.py
ai_toolkit/losses/dice.py
ai_toolkit/losses/focal.py
ai_toolkit/metrics/__init__.py
ai_toolkit/metrics/accuracy.py
ai_toolkit/metrics/dice.py
ai_toolkit/metrics/f1_score.py
ai_toolkit/metrics/iou.py
ai_toolkit/metrics/loss.py
ai_toolkit/metrics/metric.py
ai_toolkit/models/__init__.py
ai_toolkit/models/cnn.py
ai_toolkit/models/dense.py
ai_toolkit/models/efficient_net.py
ai_toolkit/models/lstm.py
ai_toolkit/models/maskrcnn.py
ai_toolkit/models/rnn.py
ai_toolkit/models/layers/__init__.py
ai_toolkit/visualizations/__init__.py
ai_toolkit/visualizations/activations.py
ai_toolkit/visualizations/class_viz.py
ai_toolkit/visualizations/confusion.py
ai_toolkit/visualizations/fooling.py
ai_toolkit/visualizations/saliency.py
ai_toolkit/visualizations/view_input.py
ai_toolkit/visualizations/viz_utils.py
tests/__init__.py
tests/metric_tracker_test.py
tests/train_test.py
tests/metrics/__init__.py
tests/metrics/accuracy_test.py
tests/metrics/loss_test.py
ai_toolkit-0.0.2.dist-info/LICENSE
ai_toolkit-0.0.2.dist-info/METADATA
ai_toolkit-0.0.2.dist-info/WHEEL
ai_toolkit-0.0.2.dist-info/top_level.txt
ai_toolkit-0.0.2.dist-info/RECORD
