Metadata-Version: 2.1
Name: ai-toolkit
Version: 0.0.2
Summary: AI Toolkit
Home-page: https://github.com/tyleryep/ai-toolkit
Author: Tyler Yep
Author-email: tyep@cs.stanford.edu
License: MIT
Platform: UNKNOWN
Classifier: License :: OSI Approved :: MIT License
Classifier: Operating System :: OS Independent
Classifier: Programming Language :: Python :: 3
Classifier: Programming Language :: Python :: 3 :: Only
Classifier: Programming Language :: Python :: 3.7
Classifier: Programming Language :: Python :: 3.8
Classifier: Programming Language :: Python :: 3.9
Classifier: Programming Language :: Python :: 3.10
Requires-Python: >=3.7
License-File: LICENSE
